django_dpo/__init__.py
django_dpo/apps.py
django_dpo/exceptions.py
django_dpo/gateway.py
django_dpo-0.0.2.dist-info/METADATA
django_dpo-0.0.2.dist-info/WHEEL
django_dpo-0.0.2.dist-info/licenses/LICENSE
django_dpo-0.0.2.dist-info/RECORD
