Metadata-Version: 2.3
Name: django-dpo
Version: 0.0.2
Summary: Django DPO Gateway Integration
Project-URL: Homepage, https://github.com/briansimpo/django-dpo
Project-URL: Issues, https://github.com/briansimpo/django-dpo/issues
Author-email: Brian Simpokolwe <briansimpokolwe@gmail.com>
License-File: LICENSE
Keywords: django dpo,django payment,dpo,payment,payment gateway
Classifier: License :: OSI Approved :: MIT License
Classifier: Operating System :: OS Independent
Classifier: Programming Language :: Python :: 3.10
Requires-Python: >=3.10
Requires-Dist: django>4.0.0
Requires-Dist: requests
